toads/RandomCipher.py
toads/__init__.py
toads/eda.py
toads/etl.py
toads/image.py
toads/ml.py
toads/preprocessing.py
toads/redis.py
toads/sql.py
toads/stats.py
toads/utils.py
toads-0.1.4.dist-info/WHEEL
toads-0.1.4.dist-info/METADATA
toads-0.1.4.dist-info/RECORD
